django_ganalytics-0.7.0.dist-info/DESCRIPTION.rst
django_ganalytics-0.7.0.dist-info/METADATA
django_ganalytics-0.7.0.dist-info/RECORD
django_ganalytics-0.7.0.dist-info/WHEEL
django_ganalytics-0.7.0.dist-info/metadata.json
django_ganalytics-0.7.0.dist-info/top_level.txt
ganalytics/__init__.py
ganalytics/models.py
ganalytics/tests.py
ganalytics/templates/ganalytics/ganalytics.js
ganalytics/templatetags/__init__.py
ganalytics/templatetags/ganalytics.py
