Metadata-Version: 2.0
Name: django-ganalytics
Version: 0.7.0
Summary: Simple Google Analytics integration for Django.
Home-page: https://github.com/rdegges/django-ganalytics
Author: Randall Degges
Author-email: rdegges@gmail.com
License: UNLICENSE
Keywords: django google analytics
Platform: UNKNOWN
Requires-Dist: Django (>=1.3.1)
